ros2_easy_test/__init__.py
ros2_easy_test/decorators.py
ros2_easy_test/env.py
ros2_easy_test/launch_file.py
ros2_easy_test/py.typed
ros2_easy_test-0.2.0.post1.dist-info/LICENSE
ros2_easy_test-0.2.0.post1.dist-info/METADATA
ros2_easy_test-0.2.0.post1.dist-info/WHEEL
ros2_easy_test-0.2.0.post1.dist-info/top_level.txt
ros2_easy_test-0.2.0.post1.dist-info/RECORD
