Metadata-Version: 2.1
Name: ros2-easy-test
Version: 0.2.0.post1
Summary: A Python test framework for ROS2 allowing simple and expressive assertions based on message interactions.
Author-email: Felix Divo <felix.divo@sailingteam.tu-darmstadt.de>
Project-URL: Homepage, https://github.com/felixdivo/ros2-easy-test
Classifier: Programming Language :: Python :: 3
Classifier: Operating System :: OS Independent
Classifier: Natural Language :: English
Classifier: License :: OSI Approved :: MIT License
Classifier: Intended Audience :: Developers
Classifier: Framework :: Robot Framework :: Library
Classifier: Topic :: Software Development :: Testing
Classifier: Topic :: Software Development :: Testing :: BDD
Classifier: Typing :: Typed
Requires-Python: >=3.8
License-File: LICENSE
Requires-Dist: makefun (>=1.15.1)
Provides-Extra: dev
Requires-Dist: black (~=23.1) ; extra == 'dev'
Requires-Dist: ruff ; extra == 'dev'
Requires-Dist: mypy (~=1.3.0) ; extra == 'dev'
Requires-Dist: pytest ; extra == 'dev'
Requires-Dist: pytest-cov ; extra == 'dev'
Requires-Dist: pytest-sugar ; extra == 'dev'
Requires-Dist: hypothesis ; extra == 'dev'
Provides-Extra: doc
Requires-Dist: sphinx ; extra == 'doc'
Requires-Dist: sphinx-rtd-theme ; extra == 'doc'
